odoo/addons/stock_move_auto_assign/README.rst
odoo/addons/stock_move_auto_assign/__init__.py
odoo/addons/stock_move_auto_assign/__manifest__.py
odoo/addons/stock_move_auto_assign/data/queue_job_channel_data.xml
odoo/addons/stock_move_auto_assign/data/queue_job_function_data.xml
odoo/addons/stock_move_auto_assign/i18n/stock_move_auto_assign.pot
odoo/addons/stock_move_auto_assign/models/__init__.py
odoo/addons/stock_move_auto_assign/models/product_product.py
odoo/addons/stock_move_auto_assign/models/stock_move.py
odoo/addons/stock_move_auto_assign/readme/CONTRIBUTORS.rst
odoo/addons/stock_move_auto_assign/readme/DESCRIPTION.rst
odoo/addons/stock_move_auto_assign/static/description/icon.png
odoo/addons/stock_move_auto_assign/static/description/index.html
odoo/addons/stock_move_auto_assign/tests/__init__.py
odoo/addons/stock_move_auto_assign/tests/common.py
odoo/addons/stock_move_auto_assign/tests/test_auto_assign.py
odoo13_addon_stock_move_auto_assign-13.0.1.1.0.dist-info/METADATA
odoo13_addon_stock_move_auto_assign-13.0.1.1.0.dist-info/WHEEL
odoo13_addon_stock_move_auto_assign-13.0.1.1.0.dist-info/top_level.txt
odoo13_addon_stock_move_auto_assign-13.0.1.1.0.dist-info/RECORD
